vxbase/__init__.py
vxbase/compress.py
vxbase/files.py
vxbase/fromenv.py
vxbase/generators.py
vxbase/logger.py
vxbase/net.py
vxbase/version.py
vxbase/vjson.py
vxbase/vtypes.py
vxbase-0.0.16.dist-info/LICENSE
vxbase-0.0.16.dist-info/METADATA
vxbase-0.0.16.dist-info/WHEEL
vxbase-0.0.16.dist-info/top_level.txt
vxbase-0.0.16.dist-info/RECORD
